dtbag/__init__.py
dtbag/preprocessing/__init__.py
dtbag/preprocessing/text_utils.py
dtbag-3.1.1.dist-info/METADATA
dtbag-3.1.1.dist-info/WHEEL
dtbag-3.1.1.dist-info/top_level.txt
dtbag-3.1.1.dist-info/RECORD
