Metadata-Version: 2.4
Name: dtbag
Version: 3.1.1
Summary: Data Tool Bag (dtbag) - A Python library for text processing, data cleaning, and similarity-based clustering of textual data
Home-page: https://github.com/abderrahmane-sakhi/dtbag
Author: Abderrahmane Sakhi
Author-email: Abderrahmane.Sakhi@gmail.com
Project-URL: Bug Reports, https://github.com/abderrahmane-sakhi/dtbag/issues
Project-URL: Source, https://github.com/abderrahmane-sakhi/dtbag
Keywords: categorical data unification,text processing,data cleaning,text normalization,string matching,similarity detection,data preprocessing,text cleaning,text unification,duplicate detection,data deduplication,text clustering,levenshtein distance,fuzzy matching,clustering algorithms,pattern recognition,natural language processing,text mining,similarity metrics,edit distance,string similarity,data science,machine learning,data analysis,ETL tools,data wrangling,information retrieval,python-lib
Classifier: Programming Language :: Python :: 3
Classifier: License :: OSI Approved :: MIT License
Classifier: Operating System :: OS Independent
Classifier: Intended Audience :: Science/Research
Classifier: Intended Audience :: Financial and Insurance Industry
Classifier: Intended Audience :: Healthcare Industry
Classifier: Intended Audience :: Manufacturing
Classifier: Intended Audience :: Developers
Classifier: Intended Audience :: Other Audience
Classifier: Topic :: Scientific/Engineering :: Information Analysis
Classifier: Topic :: Office/Business
Classifier: Topic :: Text Processing
Requires-Python: >=3.6
Dynamic: author
Dynamic: author-email
Dynamic: classifier
Dynamic: description
Dynamic: description-content-type
Dynamic: home-page
Dynamic: keywords
Dynamic: project-url
Dynamic: requires-python
Dynamic: summary
